cesar_puc_csv_converter/__init__.py
cesar_puc_csv_converter/_tests/conftest.py
cesar_puc_csv_converter/_tests/test_unit_converter.py
cesar_puc_csv_converter/_tests/test_unit_main.py
cesar_puc_csv_converter/converter.py
cesar_puc_csv_converter/main.py
cesar_puc_csv_converter-0.2.0.dist-info/entry_points.txt
cesar_puc_csv_converter-0.2.0.dist-info/LICENSE
cesar_puc_csv_converter-0.2.0.dist-info/WHEEL
cesar_puc_csv_converter-0.2.0.dist-info/METADATA
cesar_puc_csv_converter-0.2.0.dist-info/RECORD
