Metadata-Version: 2.1
Name: cesar-puc-csv-converter
Version: 0.2.0
Summary: Convert csv to json. Publishing only for learning purposes at PUC.
Home-page: https://github.com/cesarbruschetta/cesar-puc-csv-converter
License: MIT
Author: Cesar Augusto
Author-email: cesarabruschetta@gmail.com
Requires-Python: >=3.9,<4.0
Classifier: License :: OSI Approved :: MIT License
Classifier: Programming Language :: Python :: 3
Classifier: Programming Language :: Python :: 3.9
Requires-Dist: click (>=8.0.1,<9.0.0)
